{
  "visitors": [
    {
      "ip": "42.117.145.15",
      "timestamp": "2025-12-14T22:22:54.648Z",
      "device": "Desktop/Laptop",
      "browser": "Chrome",
      "os": "Windows",
      "country": "N/A",
      "city": "N/A",
      "region": "N/A",
      "screenResolution": "1280x720",
      "language": "vi-VN",
      "timezone": "Asia/Bangkok",
      "referrer": "https://expert-space-eureka-gwpq74gwvvq39x7v.github.dev/",
      "clickPosition": null,
      "fullData": {
        "ip": "42.117.145.15",
        "city": "N/A",
        "region": "N/A",
        "country": "N/A",
        "countryCode": "N/A",
        "postal": "N/A",
        "latitude": "N/A",
        "longitude": "N/A",
        "org": "N/A",
        "asn": "N/A",
        "device": "Desktop/Laptop",
        "browser": "Chrome",
        "os": "Windows",
        "userAgent": "Mozilla/5.0 (Windows NT 10.0; Win64; x64) AppleWebKit/537.36 (KHTML, like Gecko) Chrome/143.0.0.0 Safari/537.36",
        "platform": "Win32",
        "screenWidth": 1280,
        "screenHeight": 720,
        "screenResolution": "1280x720",
        "screenColorDepth": 24,
        "screenPixelDepth": 24,
        "windowWidth": 1280,
        "windowHeight": 559,
        "windowResolution": "1280x559",
        "language": "vi-VN",
        "languages": "vi-VN, vi, fr-FR, fr, en-US, en",
        "timezone": "Asia/Bangkok",
        "timezoneOffset": -420,
        "cookiesEnabled": true,
        "doNotTrack": "Not set",
        "onLine": true,
        "javaEnabled": false,
        "hardwareConcurrency": 4,
        "deviceMemory": "8 GB",
        "maxTouchPoints": 0,
        "touchSupport": false,
        "connectionType": "4g",
        "connectionDownlink": 10,
        "connectionRtt": 50,
        "referrer": "https://expert-space-eureka-gwpq74gwvvq39x7v.github.dev/",
        "pageTitle": "🎮 Lucky Spin Game",
        "pageUrl": "https://expert-space-eureka-gwpq74gwvvq39x7v-3000.app.github.dev/",
        "protocol": "https:",
        "plugins": "PDF Viewer, Chrome PDF Viewer, Chromium PDF Viewer, Microsoft Edge PDF Viewer, WebKit built-in PDF",
        "vendor": "Google Inc.",
        "localStorage": true,
        "sessionStorage": true,
        "indexedDB": true,
        "webGL": {
          "vendor": "Google Inc. (Intel)",
          "renderer": "ANGLE (Intel, Intel(R) HD Graphics 5500 (0x00001616) Direct3D11 vs_5_0 ps_5_0, D3D11)"
        },
        "canvas": "data:image/png;base64,iVBORw0KGgoAAAANSUhEUgAAASwA",
        "clickPosition": null,
        "clickTime": null,
        "timestamp": "2025-12-14T22:22:54.648Z",
        "timestampLocal": "05:22:54 15/12/2025"
      }
    }
  ]
}